collective.noindexing-2.0.0-py3.6-nspkg.pth
collective/noindexing/__init__.py
collective/noindexing/browser.py
collective/noindexing/configure.zcml
collective/noindexing/patches.py
collective/noindexing/testing.py
collective/noindexing/testing.zcml
collective/noindexing/tests/__init__.py
collective/noindexing/tests/test_functional.py
collective.noindexing-2.0.0.dist-info/METADATA
collective.noindexing-2.0.0.dist-info/WHEEL
collective.noindexing-2.0.0.dist-info/entry_points.txt
collective.noindexing-2.0.0.dist-info/namespace_packages.txt
collective.noindexing-2.0.0.dist-info/top_level.txt
collective.noindexing-2.0.0.dist-info/RECORD
