Metadata-Version: 2.1
Name: collective.noindexing
Version: 2.0.0
Summary: Ignore all indexing operations
Home-page: https://github.com/collective/collective.noindexing
Author: Maurits van Rees
Author-email: m.van.rees@zestsoftware.nl
License: GPL
Keywords: catalog index plone
Platform: UNKNOWN
Classifier: Development Status :: 5 - Production/Stable
Classifier: Framework :: Plone
Classifier: Framework :: Plone :: 4.3
Classifier: Framework :: Plone :: 5.1
Classifier: Framework :: Plone :: 5.2
Classifier: License :: OSI Approved :: GNU General Public License (GPL)
Classifier: Programming Language :: Python
Classifier: Programming Language :: Python :: 2.7
Classifier: Programming Language :: Python :: 3.6
Classifier: Programming Language :: Python :: 3.7
Requires-Dist: setuptools
Requires-Dist: Products.CMFCore
Provides-Extra: test
Requires-Dist: plone.app.testing ; extra == 'test'
Requires-Dist: unittest2 ; extra == 'test'
Requires-Dist: zope.configuration ; extra == 'test'
Requires-Dist: zope.component ; extra == 'test'
